{
"AccountsDir": "./accounts",
"BlockDBPath": "./database/blockchain",
"BootstrapNodesFilePath": "./booters/booter.txt",
"CentralConfigMode": false,
"ContractEngine": "DEMO_PIPE_CONTRACT_NAME",
"DperKeyAddress": "2a5c4688a2aa87d4bcaa497fe61313f9efd27c01",
"DperPrivateKey": "",
"DperRole": "Leader",
"ListenAddress": "127.0.0.1:20131",
"MaxPeerNum": 20,
"MemoryDBMode": false,
"NATKind": "Any",
"NewAddressMode": false,
"RemoteEnginePipeName": "/tmp/mypipename20330.sock",
"RemoteSupportPipeName": "/tmp/mypipename20230.sock",
"ServerName": "dper",
"StorageDBPath": "./database/storage",
"SubNetName": "net0"
}